blog/__init__.py
blog/adminforms.py
blog/adminx.py
blog/apps.py
blog/models.py
blog/rss.py
blog/sitemap.py
blog/tests.py
blog/views.py
blog/middleware/__init__.py
blog/middleware/user_id.py
blog/migrations/0001_initial.py
blog/migrations/0002_auto_20180310_1505.py
blog/migrations/0003_auto_20180325_1737.py
blog/migrations/0004_post_content_html.py
blog/migrations/0005_auto_20180502_1730.py
blog/migrations/__init__.py
comment/__init__.py
comment/adminx.py
comment/apps.py
comment/forms.py
comment/models.py
comment/tests.py
comment/views.py
comment/migrations/0001_initial.py
comment/migrations/0002_auto_20180410_1922.py
comment/migrations/__init__.py
comment/templatetags/__init__.py
comment/templatetags/comment_block.py
config/__init__.py
config/adminx.py
config/apps.py
config/models.py
config/tests.py
config/views.py
config/migrations/0001_initial.py
config/migrations/0002_auto_20180410_1922.py
config/migrations/__init__.py
typeidea/__init__.py
typeidea/autocomplete.py
typeidea/base_admin.py
typeidea/storage.py
typeidea/urls.py
typeidea/wsgi.py
typeidea/media/article_images/2018/04/20/grysid.jpg
typeidea/media/article_images/2018/04/21/cell.png
typeidea/media/article_images/2018/04/21/cell_isIMqw6.png
typeidea/media/article_images/2018/04/21/dj-logo.png
typeidea/media/article_images/2018/04/21/django-hexbin.png
typeidea/media/article_images/2018/04/21/qcloud_ping.png
typeidea/media/article_images/2018/05/02/cell.png
typeidea/media/article_images/2018/05/02/cell_htXNbDH.png
typeidea/settings/__init__.py
typeidea/settings/base.py
typeidea/settings/develop.py
typeidea/settings/product.py
typeidea/themes/bootstrap/static/css/bootstrap.css
typeidea/themes/bootstrap/static/css/bootstrap.min.css
typeidea/themes/bootstrap/static/js/post_editor.js
typeidea/themes/bootstrap/templates/404.html
typeidea/themes/bootstrap/templates/50x.html
typeidea/themes/bootstrap/templates/blog/base.html
typeidea-0.0.2.dist-info/DESCRIPTION.rst
typeidea-0.0.2.dist-info/METADATA
typeidea-0.0.2.dist-info/RECORD
typeidea-0.0.2.dist-info/WHEEL
typeidea-0.0.2.dist-info/entry_points.txt
typeidea-0.0.2.dist-info/metadata.json
typeidea-0.0.2.dist-info/top_level.txt
