Metadata-Version: 2.0
Name: typeidea
Version: 0.0.2
Summary: Blog System base on Django
Home-page: https://www.the5fire.com
Author: the5fire
Author-email: thefivefire@gmail.com
License: MIT
Platform: UNKNOWN
Classifier: Development Status :: 3 - Alpha
Classifier: Intended Audience :: Developers
Classifier: Topic :: Software Development :: Libraries
Classifier: License :: OSI Approved :: MIT License
Classifier: Programming Language :: Python :: 3.6
Requires-Dist: django (==2.0.6)
Requires-Dist: uWSGI (==2.0.17)
Requires-Dist: mysqlclient (==1.3.12)
Requires-Dist: django-ckeditor (==5.4.0)
Requires-Dist: django-redis (==4.8.0)
Requires-Dist: django-autocomplete-light (==3.2.10)
Requires-Dist: mistune (==0.8.3)
Requires-Dist: Pillow (==4.3.0)
Requires-Dist: django-redis (==4.8.0)
Requires-Dist: hiredis (==0.2.0)
Requires-Dist: django-simple-captcha (==0.5.7)
